siemensfile/__init__.py
siemensfile/ismrmrd_formato.py
siemensfile/reconstruction copy.py
siemensfile/reconstruction.py
siemensfile/siemensfile copy.py
siemensfile/siemensfile.py
siemensfile/utils.py
src/__init__.py
src/siemensfile/__init__.py
src/siemensfile/core.py
src/siemensfile/reconstruction.py
src/siemensfile/siemensfile.py
src/siemensfile/utils.py
src/twixtools/__init__.py
src/twixtools/geometry.py
src/twixtools/hdr_def.py
src/twixtools/helpers.py
src/twixtools/map_twix.py
src/twixtools/mdb.py
src/twixtools/mdh_def.py
src/twixtools/pmu.py
src/twixtools/quat.py
src/twixtools/recon_helpers.py
src/twixtools/twixprot.py
src/twixtools/twixtools.py
src/twixtools/twixzip.py
twixtools/__init__.py
twixtools/geometry.py
twixtools/hdr_def.py
twixtools/helpers.py
twixtools/map_twix.py
twixtools/mdb.py
twixtools/mdh_def.py
twixtools/pmu.py
twixtools/quat.py
twixtools/recon_helpers.py
twixtools/twixprot.py
twixtools/twixtools.py
twixtools/twixzip.py
siemensfile-0.1.30.dist-info/LICENSE
siemensfile-0.1.30.dist-info/METADATA
siemensfile-0.1.30.dist-info/WHEEL
siemensfile-0.1.30.dist-info/top_level.txt
siemensfile-0.1.30.dist-info/RECORD
