Metadata-Version: 2.1
Name: siemensfile
Version: 0.1.30
Summary: Paquete para leer archivos .dat de Siemens y realizar reconstrucciones de imágenes.
Home-page: https://github.com/cenarius1985/SIEMENSFile
Author: Fernando Jose Ramirez
Author-email: fernando.ramirez.sarmiento@gmail.com
Classifier: Programming Language :: Python :: 3
Classifier: License :: OSI Approved :: MIT License
Classifier: Operating System :: OS Independent
Requires-Python: >=3.12.4
License-File: LICENSE
Requires-Dist: numpy
Requires-Dist: pandas
Requires-Dist: matplotlib
Requires-Dist: mri-nufft
Requires-Dist: pydicom
Requires-Dist: openpyxl
Requires-Dist: h5py
